tests/__init__.py
tests/causal_manager_validator.py
tests/common_utils.py
tests/conftest.py
tests/counterfactual_manager_validator.py
tests/error_analysis_validator.py
tests/explainer_manager_validator.py
tests/test_data_validations.py
tests/test_dependencies.py
tests/test_exceptions.py
tests/test_feature_metadata.py
tests/test_model_serializer.py
tests/test_serialization_utilities.py
tests/test_utils.py
tests/causal/__init__.py
tests/causal/conftest.py
tests/causal/test_causal_constants.py
tests/causal/test_causal_different_data_types.py
tests/causal/test_causal_general.py
tests/causal/test_causal_manager.py
tests/causal/test_causal_result.py
tests/causal/test_causal_result_versioning.py
tests/counterfactual/__init__.py
tests/counterfactual/test_counterfactual_advanced_features.py
tests/databalanceanalysis/__init__.py
tests/databalanceanalysis/conftest.py
tests/databalanceanalysis/test_aggregate_balance_measures.py
tests/databalanceanalysis/test_data_balance_helper.py
tests/databalanceanalysis/test_data_balance_manager.py
tests/databalanceanalysis/test_distribution_balance_measures.py
tests/databalanceanalysis/test_feature_balance_measures.py
tests/explainer/__init__.py
tests/explainer/test_explainer_manager.py
tests/model_analysis/__init__.py
tests/model_analysis/test_model_analysis.py
tests/model_analysis/test_model_analysis_validations.py
tests/tai_insights/__init__.py
tests/tai_insights/test_served_model.py
tests/tai_insights/test_tai_insights.py
tests/tai_insights/test_tai_insights_cohort_filter.py
tests/tai_insights/test_tai_insights_data_size_scenarios.py
tests/tai_insights/test_tai_insights_get_feature_ranges.py
tests/tai_insights/test_tai_insights_missing_values.py
tests/tai_insights/test_tai_insights_save_and_load_scenarios.py
tests/tai_insights/test_tai_insights_validations.py
tests/tools/__init__.py
tests/tools/shared/__init__.py
tests/tools/shared/test_attribute_serialization.py
tests/tools/shared/test_state_directory_management.py
trustworthyai-0.35.0.dist-info/LICENSE
trustworthyai-0.35.0.dist-info/METADATA
trustworthyai-0.35.0.dist-info/WHEEL
trustworthyai-0.35.0.dist-info/top_level.txt
trustworthyai-0.35.0.dist-info/RECORD
